{
  "version": "7",
  "dialect": "postgresql",
  "entries": [
    {
      "idx": 0,
      "version": "7",
      "when": 1784598494508,
      "tag": "0000_init",
      "breakpoints": true
    },
    {
      "idx": 1,
      "version": "7",
      "when": 1784604333079,
      "tag": "0001_misty_skaar",
      "breakpoints": true
    },
    {
      "idx": 2,
      "version": "7",
      "when": 1784648829007,
      "tag": "0002_flawless_gargoyle",
      "breakpoints": true
    },
    {
      "idx": 3,
      "version": "7",
      "when": 1784651393056,
      "tag": "0003_sticky_marten_broadcloak",
      "breakpoints": true
    }
  ]
}